LICENSE
README.md
pyproject.toml
src/roblox_game_performance.egg-info/PKG-INFO
src/roblox_game_performance.egg-info/SOURCES.txt
src/roblox_game_performance.egg-info/dependency_links.txt
src/roblox_game_performance.egg-info/requires.txt
src/roblox_game_performance.egg-info/top_level.txt
src/rogameperf/__init__.py