Metadata-Version: 2.1
Name: roblox-game-performance
Version: 0.1.4
Summary: a python package which scrapes the roblox website for advertisement and game metrics, useful for game analytics
Author-email: nightcycle <coyer@nightcycle.us>
Classifier: Programming Language :: Python :: 3
Classifier: Operating System :: OS Independent
Requires-Python: >=3.10
License-File: LICENSE
